README.rst
setup.py
samsung_print/__init__.py
samsung_print/exceptions.py
samsung_print.egg-info/PKG-INFO
samsung_print.egg-info/SOURCES.txt
samsung_print.egg-info/dependency_links.txt
samsung_print.egg-info/requires.txt
samsung_print.egg-info/top_level.txt
samsung_print.egg-info/zip-safe