Metadata-Version: 1.2
Name: samsung-print
Version: 0.2.0
Summary: Python API for interacting with devices from Samsung.
Home-page: https://github.com/fabaff/samsung_print
Author: Fabian Affolter
Author-email: fabian@affolter-engineering.ch
License: MIT
Download-URL: https://github.com/fabaff/samsung_print/releases
Platform: UNKNOWN
Classifier: Development Status :: 3 - Alpha
Classifier: Environment :: Console
Classifier: Intended Audience :: Developers
Classifier: License :: OSI Approved :: MIT License
Classifier: Operating System :: MacOS :: MacOS X
Classifier: Operating System :: Microsoft :: Windows
Classifier: Operating System :: POSIX
Classifier: Programming Language :: Python :: 3.5
Classifier: Topic :: Utilities
Requires-Python: >=3.5
